nvchecker/__init__.py
nvchecker/__main__.py
nvchecker/api.py
nvchecker/core.py
nvchecker/ctxvars.py
nvchecker/slogconf.py
nvchecker/sortversion.py
nvchecker/tools.py
nvchecker/util.py
nvchecker/httpclient/__init__.py
nvchecker/httpclient/aiohttp_httpclient.py
nvchecker/httpclient/base.py
nvchecker/httpclient/httpx_httpclient.py
nvchecker/httpclient/tornado_httpclient.py
nvchecker/lib/__init__.py
nvchecker/lib/nicelogger.py
nvchecker/lib/packaging_version.py
nvchecker-2.20.data/scripts/nvchecker-ini2toml
nvchecker-2.20.data/scripts/nvchecker-notify
nvchecker-2.20.dist-info/licenses/LICENSE
nvchecker_source/alpm.py
nvchecker_source/alpmfiles.py
nvchecker_source/android_sdk.py
nvchecker_source/anitya.py
nvchecker_source/apt.py
nvchecker_source/archpkg.py
nvchecker_source/aur.py
nvchecker_source/bitbucket.py
nvchecker_source/cmd.py
nvchecker_source/combiner.py
nvchecker_source/container.py
nvchecker_source/cpan.py
nvchecker_source/cran.py
nvchecker_source/cratesio.py
nvchecker_source/debianpkg.py
nvchecker_source/gems.py
nvchecker_source/git.py
nvchecker_source/gitea.py
nvchecker_source/github.py
nvchecker_source/gitlab.py
nvchecker_source/go.py
nvchecker_source/hackage.py
nvchecker_source/htmlparser.py
nvchecker_source/httpheader.py
nvchecker_source/jq.py
nvchecker_source/launchpad.py
nvchecker_source/manual.py
nvchecker_source/maven.py
nvchecker_source/mercurial.py
nvchecker_source/none.py
nvchecker_source/npm.py
nvchecker_source/opam.py
nvchecker_source/openvsx.py
nvchecker_source/packagist.py
nvchecker_source/pacman.py
nvchecker_source/pagure.py
nvchecker_source/pypi.py
nvchecker_source/regex.py
nvchecker_source/repology.py
nvchecker_source/rpmrepo.py
nvchecker_source/snapcraft.py
nvchecker_source/sparkle.py
nvchecker_source/ubuntupkg.py
nvchecker_source/vsmarketplace.py
nvchecker-2.20.dist-info/METADATA
nvchecker-2.20.dist-info/WHEEL
nvchecker-2.20.dist-info/entry_points.txt
nvchecker-2.20.dist-info/top_level.txt
nvchecker-2.20.dist-info/zip-safe
nvchecker-2.20.dist-info/RECORD
