Metadata-Version: 2.4
Name: nvchecker
Version: 2.20
Summary: New version checker for software
Home-page: https://github.com/lilydjwg/nvchecker
Author: lilydjwg
Author-email: lilydjwg@gmail.com
License: MIT
Keywords: new,version,build,check
Platform: any
Classifier: Development Status :: 5 - Production/Stable
Classifier: Environment :: Console
Classifier: Intended Audience :: Developers
Classifier: Intended Audience :: System Administrators
Classifier: License :: OSI Approved :: MIT License
Classifier: Operating System :: OS Independent
Classifier: Programming Language :: Python
Classifier: Programming Language :: Python :: 3
Classifier: Programming Language :: Python :: 3 :: Only
Classifier: Programming Language :: Python :: 3.8
Classifier: Programming Language :: Python :: 3.9
Classifier: Programming Language :: Python :: 3.10
Classifier: Programming Language :: Python :: 3.11
Classifier: Programming Language :: Python :: 3.12
Classifier: Programming Language :: Python :: 3.13
Classifier: Programming Language :: Python :: 3.14
Classifier: Topic :: Internet
Classifier: Topic :: Internet :: WWW/HTTP
Classifier: Topic :: Software Development
Classifier: Topic :: System :: Archiving :: Packaging
Classifier: Topic :: System :: Software Distribution
Classifier: Topic :: Utilities
Requires-Python: >=3.8
License-File: LICENSE
Requires-Dist: tomli; python_version < "3.11"
Requires-Dist: structlog
Requires-Dist: platformdirs
Requires-Dist: tornado>=6
Requires-Dist: pycurl
Provides-Extra: vercmp
Requires-Dist: pyalpm; extra == "vercmp"
Provides-Extra: awesomeversion
Requires-Dist: awesomeversion; extra == "awesomeversion"
Provides-Extra: pypi
Requires-Dist: packaging; extra == "pypi"
Provides-Extra: htmlparser
Requires-Dist: lxml; extra == "htmlparser"
Provides-Extra: rpmrepo
Requires-Dist: lxml; extra == "rpmrepo"
Requires-Dist: zstandard; python_version < "3.14" and extra == "rpmrepo"
Provides-Extra: jq
Requires-Dist: jq; extra == "jq"
Dynamic: license-file
